zlsrc/__init__.py
zlsrc/data.py
zlsrc/data_cdc.py
zlsrc/data_old.py
zlsrc/est_data.py
zlsrc/anhui/__init__.py
zlsrc/anhui/anhui_anhuisheng_1_daili.py
zlsrc/anhui/anhui_anhuisheng_1_ggzy.py
zlsrc/anhui/anhui_anhuisheng_2_daili.py
zlsrc/anhui/anhui_anhuisheng_2_ggzy.py
zlsrc/anhui/anhui_anhuisheng_daili.py
zlsrc/anhui/anhui_anhuisheng_gcjs.py
zlsrc/anhui/anhui_anhuisheng_ggzy.py
zlsrc/anhui/anhui_anhuisheng_zfcg.py
zlsrc/anhui/anhui_anqing_ggzy.py
zlsrc/anhui/anhui_anqing_zfcg.py
zlsrc/anhui/anhui_bengbu_ggzy.py
zlsrc/anhui/anhui_bengbu_zfcg.py
zlsrc/anhui/anhui_bozhou_ggzy.py
zlsrc/anhui/anhui_chaohu_ggzy.py
zlsrc/anhui/anhui_chizhou_ggzy.py
zlsrc/anhui/anhui_chuzhou_ggzy.py
zlsrc/anhui/anhui_fuyang_ggzy.py
zlsrc/anhui/anhui_hefei_gcjs.py
zlsrc/anhui/anhui_hefei_ggzy.py
zlsrc/anhui/anhui_huaibei_ggzy.py
zlsrc/anhui/anhui_huainan_1_ggzy.py
zlsrc/anhui/anhui_huainan_gcjs.py
zlsrc/anhui/anhui_huainan_ggzy.py
zlsrc/anhui/anhui_huainan_zfcg.py
zlsrc/anhui/anhui_huangshan_ggzy.py
zlsrc/anhui/anhui_luan_1_zfcg.py
zlsrc/anhui/anhui_luan_ggzy.py
zlsrc/anhui/anhui_luan_zfcg.py
zlsrc/anhui/anhui_maanshan_ggzy.py
zlsrc/anhui/anhui_suzhou_ggzy.py
zlsrc/anhui/anhui_tongling_ggzy.py
zlsrc/anhui/anhui_wuhu_1_zfcg.py
zlsrc/anhui/anhui_wuhu_ggzy.py
zlsrc/anhui/anhui_wuhu_zfcg.py
zlsrc/anhui/anhui_xuancheng_gcjs.py
zlsrc/anhui/anhui_xuancheng_ggzy.py
zlsrc/beijing/__init__.py
zlsrc/beijing/beijing_beijingshi_1_zfcg.py
zlsrc/beijing/beijing_beijingshi_daili.py
zlsrc/beijing/beijing_beijingshi_gcjs.py
zlsrc/beijing/beijing_beijingshi_ggzy.py
zlsrc/beijing/beijing_beijingshi_zfcg.py
zlsrc/beijing/beijing_haidian_ggzy.py
zlsrc/beijing/beijing_mentougou_zfcg.py
zlsrc/chongqing/__init__.py
zlsrc/chongqing/chongqing_banan_ggzy.py
zlsrc/chongqing/chongqing_chongqingshi_gcjs.py
zlsrc/chongqing/chongqing_chongqingshi_ggzy.py
zlsrc/chongqing/chongqing_chongqingshi_zfcg.py
zlsrc/chongqing/chongqing_dazu_ggzy.py
zlsrc/chongqing/chongqing_jiangbei_ggzy.py
zlsrc/chongqing/chongqing_nanchuan_zfcg.py
zlsrc-1.0.42.dist-info/METADATA
zlsrc-1.0.42.dist-info/WHEEL
zlsrc-1.0.42.dist-info/top_level.txt
zlsrc-1.0.42.dist-info/RECORD
