Metadata-Version: 2.1
Name: zlsrc
Version: 1.0.42
Summary: 深圳市筑龙科技的工作-筑龙爬虫源码
Home-page: https://github.com/lanmengfei/testdm
Author: lanmengfei
Author-email: 865377886@qq.com
License: UNKNOWN
Platform: UNKNOWN
Classifier: Environment :: Web Environment
Classifier: Intended Audience :: Developers
Classifier: Operating System :: OS Independent
Classifier: Topic :: Text Processing :: Indexing
Classifier: Topic :: Utilities
Classifier: Topic :: Internet
Classifier: Topic :: Software Development :: Libraries :: Python Modules
Classifier: Programming Language :: Python
Classifier: Programming Language :: Python :: 3
Classifier: Programming Language :: Python :: 3.5
Requires-Dist: pandas (>=0.13)
Requires-Dist: beautifulsoup4 (>=4.6.3)
Requires-Dist: cx-Oracle
Requires-Dist: numpy
Requires-Dist: psycopg2-binary
Requires-Dist: selenium
Requires-Dist: xlsxwriter
Requires-Dist: xlrd
Requires-Dist: requests
Requires-Dist: lxml
Requires-Dist: sqlalchemy
Requires-Dist: pymssql
Requires-Dist: jieba
Requires-Dist: mysqlclient
Requires-Dist: lmf (>=2.0.6)
Requires-Dist: lmfscrap (>=1.1.2)
Requires-Dist: zlhawq (>=1.8.3)
Requires-Dist: zltask (>=1.2.37)
Requires-Dist: opencv-python
Requires-Dist: scikit-learn
